pyobjloader/__init__.py
pyobjloader/model.py
pyobjloader-0.0.7.dist-info/LICENSE.txt
pyobjloader-0.0.7.dist-info/METADATA
pyobjloader-0.0.7.dist-info/WHEEL
pyobjloader-0.0.7.dist-info/top_level.txt
pyobjloader-0.0.7.dist-info/RECORD
