Metadata-Version: 2.1
Name: pyobjloader
Version: 0.0.7
Summary: An obj model loader for Python
Home-page: https://github.com/JonahCoffelt/PyObjLoader
Author: Jonah Coffelt
Author-email: coffelt.jonah@gmail.com
License-File: LICENSE.txt
Requires-Dist: numpy
Requires-Dist: PyGLM
